vscode_icons/__init__.py
vscode_icons/vscode.py
vscode_icons/static/vscode_icons/vsicons-icon-theme.json
vscode_icons/static/vscode_icons/icons/default_file.svg
vscode_icons/static/vscode_icons/icons/default_folder.svg
vscode_icons/static/vscode_icons/icons/default_folder_opened.svg
vscode_icons/static/vscode_icons/icons/default_root_folder.svg
vscode_icons/static/vscode_icons/icons/default_root_folder_opened.svg
vscode_icons/static/vscode_icons/icons/file_type_access.svg
vscode_icons/static/vscode_icons/icons/file_type_access2.svg
vscode_icons/static/vscode_icons/icons/file_type_actionscript.svg
vscode_icons/static/vscode_icons/icons/file_type_actionscript2.svg
vscode_icons/static/vscode_icons/icons/file_type_ada.svg
vscode_icons/static/vscode_icons/icons/file_type_advpl.svg
vscode_icons/static/vscode_icons/icons/file_type_affectscript.svg
vscode_icons/static/vscode_icons/icons/file_type_affinitydesigner.svg
vscode_icons/static/vscode_icons/icons/file_type_affinityphoto.svg
vscode_icons/static/vscode_icons/icons/file_type_affinitypublisher.svg
vscode_icons/static/vscode_icons/icons/file_type_ai.svg
vscode_icons/static/vscode_icons/icons/file_type_ai2.svg
vscode_icons/static/vscode_icons/icons/file_type_al.svg
vscode_icons/static/vscode_icons/icons/file_type_al_dal.svg
vscode_icons/static/vscode_icons/icons/file_type_allcontributors.svg
vscode_icons/static/vscode_icons/icons/file_type_angular.svg
vscode_icons/static/vscode_icons/icons/file_type_ansible.svg
vscode_icons/static/vscode_icons/icons/file_type_antlr.svg
vscode_icons/static/vscode_icons/icons/file_type_anyscript.svg
vscode_icons/static/vscode_icons/icons/file_type_apache.svg
vscode_icons/static/vscode_icons/icons/file_type_apex.svg
vscode_icons/static/vscode_icons/icons/file_type_api_extractor.svg
vscode_icons/static/vscode_icons/icons/file_type_apib.svg
vscode_icons/static/vscode_icons/icons/file_type_apib2.svg
vscode_icons/static/vscode_icons/icons/file_type_apl.svg
vscode_icons-1.0.0.dist-info/METADATA
vscode_icons-1.0.0.dist-info/WHEEL
vscode_icons-1.0.0.dist-info/top_level.txt
vscode_icons-1.0.0.dist-info/RECORD
