Metadata-Version: 2.1
Name: vscode-icons
Version: 1.0.0
Summary: Django app to provide vscode icons for web application.
Author: Tahir Rafique
Author-email: tahirrafiqueasad@gmail.com
License: MIT
Keywords: vscode,icons,vscode icons,django icons
Classifier: Framework :: Django :: 3.2
Classifier: Topic :: Software Development :: Libraries :: Python Modules
Classifier: Development Status :: 5 - Production/Stable
Classifier: License :: OSI Approved :: MIT License
Classifier: Programming Language :: Python :: 3
Classifier: Programming Language :: Python :: 3.7
Classifier: Programming Language :: Python :: 3.8
Classifier: Operating System :: OS Independent
Classifier: Environment :: Web Environment
Classifier: Intended Audience :: Developers
Classifier: Intended Audience :: Science/Research
Classifier: Intended Audience :: Information Technology
Classifier: Natural Language :: English
Requires-Dist: django (>=3.2.10)
